alana/__init__.py
alana/aliases.py
alana/color.py
alana/globals.py
alana/prompt.py
alana/prompt_async.py
alana-0.0.10.dist-info/LICENSE
alana-0.0.10.dist-info/METADATA
alana-0.0.10.dist-info/WHEEL
alana-0.0.10.dist-info/top_level.txt
alana-0.0.10.dist-info/RECORD
