Metadata-Version: 2.1
Name: alana
Version: 0.0.10
Summary: Utilities for Alana, and maybe you too. Mostly geared toward LLM-heavy workflows.
Home-page: https://github.com/alat-rights/alana-utilities
Author: Alana
Author-email: hi@alana.computer
Keywords: LLM,utilities
Classifier: Development Status :: 3 - Alpha
Classifier: Intended Audience :: Developers
Classifier: License :: OSI Approved :: MIT License
Classifier: Programming Language :: Python :: 3
Classifier: Programming Language :: Python :: 3.6
Classifier: Programming Language :: Python :: 3.7
Classifier: Programming Language :: Python :: 3.8
Classifier: Programming Language :: Python :: 3.9
Requires-Python: >=3.6
License-File: LICENSE
Requires-Dist: anthropic
Requires-Dist: colorama
Requires-Dist: numpy
